potatoscript/potatoConfig.py
potatoConfig-1.0.0.dist-info/METADATA
potatoConfig-1.0.0.dist-info/WHEEL
potatoConfig-1.0.0.dist-info/top_level.txt
potatoConfig-1.0.0.dist-info/RECORD
